{
  "drops": {
    "bySiteCanonical": {
      "underdog": {
        "invalid_odds": 22,
        "line_mismatch": 275,
        "no_match": 239
      }
    },
    "bySportCanonical": {
      "NBA": {
        "invalid_odds": 22,
        "line_mismatch": 275,
        "no_match": 239
      }
    },
    "byStatCanonical": {
      "assists": {
        "invalid_odds": 3,
        "no_match": 21
      },
      "blocks": {
        "no_match": 4
      },
      "points": {
        "invalid_odds": 9,
        "line_mismatch": 275,
        "no_match": 165
      },
      "rebounds": {
        "invalid_odds": 2,
        "no_match": 24
      },
      "steals": {
        "invalid_odds": 2,
        "no_match": 14
      },
      "turnovers": {
        "invalid_odds": 6,
        "no_match": 11
      }
    }
  },
  "generatedAtUtc": "2026-03-29T00:38:11.234Z",
  "matches": {
    "altPoolMatchesBySite": {
      "underdog": 34
    },
    "lineKindBySite": {
      "underdog": {
        "exact": 110,
        "nearest": 11,
        "total": 121
      }
    },
    "matchTypeBySite": {
      "underdog": {
        "alt": 34,
        "main": 87
      }
    }
  },
  "merged": {
    "altPoolMatchCountByStat": {
      "assists": 7,
      "points": 12,
      "rebounds": 10,
      "turnovers": 5
    },
    "lineDeltaHistogramByStat": {
      "assists": {
        "0": 23,
        "1.00": 3
      },
      "points": {
        "0": 44,
        "1.00": 8
      },
      "rebounds": {
        "0": 35
      },
      "steals": {
        "0": 3
      },
      "turnovers": {
        "0": 5
      }
    }
  },
  "mergedLineDeltaHistogram": {
    "0": 110,
    "1.00": 11
  },
  "schemaVersion": 1,
  "sourceAuditGeneratedAtUtc": "2026-03-29T00:38:11.234Z"
}
